nonebot_plugin_fuckfinalshell/__init__.py
nonebot_plugin_fuckfinalshell-0.1.2.dist-info/METADATA
nonebot_plugin_fuckfinalshell-0.1.2.dist-info/WHEEL
nonebot_plugin_fuckfinalshell-0.1.2.dist-info/licenses/LICENSE
nonebot_plugin_fuckfinalshell-0.1.2.dist-info/RECORD
