Metadata-Version: 2.4
Name: nonebot-plugin-fuckfinalshell
Version: 0.1.2
Summary: 基于 Nonebot2 的 FinalShell 激活码生成插件
Project-URL: Repository, https://github.com/006lp/nonebot-plugin-fuckfinalshell
Author-email: 006lp <006lpsuki@gmail.com>
License-File: LICENSE
Requires-Python: >=3.10
Requires-Dist: nonebot2>=2.4.2
Requires-Dist: pycryptodome>=3.23.0
